Metadata-Version: 2.1
Name: jahnaviPython
Version: 0.0.1
Summary: this is a trial package used for calculation.
Home-page: UNKNOWN
Author: Jahnavi Manjunath
Author-email: jahnavi2207@gmail.com
License: MIT
Platform: UNKNOWN
License-File: LICENCE.txt
